shadowsocksr/__init__.py
shadowsocksr/apiconfig.py
shadowsocksr/asyncmgr.py
shadowsocksr/configloader.py
shadowsocksr/db_transfer.py
shadowsocksr/importloader.py
shadowsocksr/mujson_mgr.py
shadowsocksr/server.py
shadowsocksr/server_pool.py
shadowsocksr/setup.py
shadowsocksr/switchrule.py
shadowsocksr/shadowsocks/__init__.py
shadowsocksr/shadowsocks/asyncdns.py
shadowsocksr/shadowsocks/common.py
shadowsocksr/shadowsocks/daemon.py
shadowsocksr/shadowsocks/encrypt.py
shadowsocksr/shadowsocks/encrypt_test.py
shadowsocksr/shadowsocks/entry.py
shadowsocksr/shadowsocks/eventloop.py
shadowsocksr/shadowsocks/local.py
shadowsocksr/shadowsocks/lru_cache.py
shadowsocksr/shadowsocks/manager.py
shadowsocksr/shadowsocks/obfs.py
shadowsocksr/shadowsocks/ordereddict.py
shadowsocksr/shadowsocks/server.py
shadowsocksr/shadowsocks/shell.py
shadowsocksr/shadowsocks/tcprelay.py
shadowsocksr/shadowsocks/udprelay.py
shadowsocksr/shadowsocks/version.py
shadowsocksr/shadowsocks/crypto/__init__.py
shadowsocksr/shadowsocks/crypto/ctypes_libsodium.py
shadowsocksr/shadowsocks/crypto/ctypes_openssl.py
shadowsocksr/shadowsocks/crypto/openssl.py
shadowsocksr/shadowsocks/crypto/rc4_md5.py
shadowsocksr/shadowsocks/crypto/sodium.py
shadowsocksr/shadowsocks/crypto/table.py
shadowsocksr/shadowsocks/crypto/util.py
shadowsocksr/shadowsocks/obfsplugin/__init__.py
shadowsocksr/shadowsocks/obfsplugin/auth.py
shadowsocksr/shadowsocks/obfsplugin/auth_chain.py
shadowsocksr/shadowsocks/obfsplugin/http_simple.py
shadowsocksr/shadowsocks/obfsplugin/obfs_tls.py
shadowsocksr/shadowsocks/obfsplugin/plain.py
shadowsocksr/shadowsocks/obfsplugin/verify.py
essr-0.0.1a1.dist-info/METADATA
essr-0.0.1a1.dist-info/WHEEL
essr-0.0.1a1.dist-info/entry_points.txt
essr-0.0.1a1.dist-info/top_level.txt
essr-0.0.1a1.dist-info/RECORD
