Metadata-Version: 2.1
Name: essr
Version: 0.0.1a1
Summary: Electronic SSR
Home-page: https://github.com/GaoangLiu/ssr
Author: Gaogle
Author-email: byteleap@gmail.com
License: UNKNOWN
Platform: UNKNOWN
Classifier: Programming Language :: Python :: 3
Classifier: License :: OSI Approved :: MIT License
Classifier: Operating System :: OS Independent
